makdo/__init__.py
makdo/eblook.py
makdo/keiji.py
makdo/makdo_docx2md.py
makdo/makdo_editor.py
makdo/makdo_md2docx.py
makdo/makdo_mddiff.py
makdo-8.19.dist-info/LICENSE
makdo-8.19.dist-info/METADATA
makdo-8.19.dist-info/WHEEL
makdo-8.19.dist-info/top_level.txt
makdo-8.19.dist-info/RECORD
