Metadata-Version: 2.1
Name: makdo
Version: 8.19
Summary: MS WordのファイルをMarkdownで作成・編集します
Home-page: https://github.com/hata48915b/makdo/
Author: Seiichiro HATA
Author-email: hata48915b@post.nifty.jp
License: GPLv3+
License-File: LICENSE
Requires-Dist: Levenshtein
Requires-Dist: chardet
Requires-Dist: openpyxl
Requires-Dist: python-docx
Requires-Dist: tkinterdnd2
